{
	"default_connection": {
		"host": "localhost",
		"port": 5432,
		"user": "postgres",
		"password": "postgres",
		"dbname": "postgres",
		"autocommit": true
	},
	"service": {
		"postgresql": "postgresql-x64-15"
	},
	"users": [
		{
			"user": "builder",
			"password": "...",
			"superuser": true
		},
		{
			"user": "client",
			"password": "...",
			"superuser": false
		}
	],
	"databases": [
		{
			"database": "btc_address_lookup",
			"owner": "builder",
			"tables": [
				{
					"table_name": "currency",
					"create": [
						"currency_id SMALLSERIAL NOT NULL",
						"name TEXT NOT NULL",
						"code TEXT NOT NULL",
						"logo TEXT NOT NULL",
						"blockchair_request_name TEXT",
						"CONSTRAINT currency_currency_id_pkey PRIMARY KEY (currency_id)",
						"CONSTRAINT currency_name_key UNIQUE (name)",
						"CONSTRAINT currency_code_key UNIQUE (code)",
						"CONSTRAINT currency_logo_key UNIQUE (logo)",
						"CONSTRAINT blockchair_request_name_key UNIQUE (blockchair_request_name)"
					],
					"insert": [
						["name", "code", "logo", "blockchair_request_name"],
						[
							["Bitcoin", "BTC", "/src/img/BTC.svg", "bitcoin"],
							["Unknown", "N/A", "/src/img/unknown.svg", null],
							["Ethereum", "ETH", "/src/img/ETH.svg", "ethereum"],
							["Cardano", "ADA", "/src/img/ADA.svg", "cardano"],
							["Bitcoin Cash", "BCH", "/src/img/BCH.svg", "bitcoin-cash"],
							["BNB", "BNB", "/src/img/BNB.svg", "bnb"],
							["Dash", "DASH", "/src/img/DASH.svg", "dash"],
							["Dogecoin", "DOGE", "/src/img/DOGE.svg", "dogecoin"],
							["Polkadot", "DOT", "/src/img/DOT.svg", "polkadot"],
							["EOS", "EOS", "/src/img/EOS.svg", "eos"],
							["Groestlcoin", "GRS", "/src/img/GRS.svg", "groestlcoin"],
							["Kusama", "KSM", "/src/img/KSM.svg", "kusama"],
							["Litecoin", "LTC", "/src/img/LTC.svg", "litecoin"],
							["eCash", "XEC", "/src/img/XEC.svg", "ecash"],
							["Mixin", "XIN", "/src/img/XIN.svg", "mixin"],
							["Stellar", "XLM", "/src/img/XLM.svg", "stellar"],
							["Monero", "XMR", "/src/img/XMR.svg", "monero"],
							["Ripple", "XRP", "/src/img/XRP.svg", "ripple"],
							["Zcash", "ZEC", "/src/img/ZEC.svg", "zcash"]
						]
					]
				},
				{
					"table_name": "source",
					"create": [
						"source_id SMALLSERIAL NOT NULL",
						"roles SMALLINT[] NOT NULL",
						"name TEXT NOT NULL",
						"CONSTRAINT source_source_id_pkey PRIMARY KEY (source_id)",
						"CONSTRAINT source_name_key UNIQUE (name)"
					],
					"insert": [
						["roles", "name"],
						[
							["{}", "LoyceV"],
							["{}", "BitcoinAbuse"],
							["{}", "CheckBitcoinAddress"],
							["{}", "CryptoBlacklist"],
							["{}", "Bitcoin Generator Scam"],
							["{}", "BitcoinAIS"],
							["{}", "CryptoScamDB"],
							["{}", "Cryptscam"],
							["{}", "SeeKoin"],
							["{}", "BitcoinWhosWho"]
						]
					]
				},
				{
					"table_name": "source_label",
					"create": [
						"source_label_id SMALLSERIAL",
						"source_id SMALLINT NOT NULL",
						"new_addresses_currency_id SMALLINT",
						"roles SMALLINT[] NOT NULL",
						"name TEXT NOT NULL",
						"CONSTRAINT source_label_source_label_id_pkey PRIMARY KEY (source_label_id)",
						"CONSTRAINT source_label_source_id_fkey FOREIGN KEY (source_id) REFERENCES source (source_id)",
						"CONSTRAINT source_label_new_addresses_currency_id_fkey FOREIGN KEY (new_addresses_currency_id) REFERENCES currency (currency_id)",
						"CONSTRAINT source_label_source_id_name_key UNIQUE (source_id, name)",
						"CONSTRAINT source_label_source_id_check CHECK (source_id > 0)",
						"CONSTRAINT source_label_new_addresses_currency_id_check CHECK (new_addresses_currency_id > 0)"
					],
					"insert": [
						["source_id", "new_addresses_currency_id", "roles", "name"],
						[
							["1", 1, "{}", "All BTC Addresses"],
							["2", null, "{}", "Reported BTC Addresses"],
							["3", null, "{}", "Reported BTC Addresses"],
							["4", null, "{}", "Searched Reported BTC Addresses"],
							["4", 3, "{}", "Last Reported Ethereum Addresses"],
							["5", null, "{}", "Scam BTC Addresses"],
							["5", 2, "{}", "Scam Non-BTC Addresses"],
							["6", null, "{}", "Reported BTC Addresses"],
							["7", 2, "{}", "Reported Addresses"],
							["8", null, "{}", "Searched Reported BTC Addresses"],
							["8", 2, "{}", "Last Reported Addresses"],
							["9", null, "{}", "Reported BTC Addresses"],
							["10", null, "{}", "Searched Reported BTC Addresses"]
						]
					]
				},
				{
					"table_name": "address",
					"create": [
						"address_id BIGSERIAL",
						"currency_id SMALLINT",
						"source_label_id SMALLINT NOT NULL",
						"address TEXT NOT NULL",
						"CONSTRAINT address_address_id_pkey PRIMARY KEY (address_id)",
						"CONSTRAINT address_currency_id_fkey FOREIGN KEY (currency_id) REFERENCES currency (currency_id)",
						"CONSTRAINT address_source_label_id_fkey FOREIGN KEY (source_label_id) REFERENCES source_label (source_label_id)",
						"CONSTRAINT address_address_key UNIQUE (address)",
						"CONSTRAINT address_currency_id_check CHECK (currency_id > 0)",
						"CONSTRAINT address_source_label_id_check CHECK (source_label_id > 0)"
					]
				},
				{
					"table_name": "url",
					"create": [
						"url_id BIGSERIAL",
						"address TEXT NOT NULL",
						"CONSTRAINT url_url_id_pkey PRIMARY KEY (url_id)",
						"CONSTRAINT url_address_key UNIQUE (address)"
					],
					"insert": [
						["address"],
						[
							["http://alladdresses.loyce.club/all_Bitcoin_addresses_ever_used_in_order_of_first_appearance.txt.gz"],
							["http://alladdresses.loyce.club/daily_updates"],
							["https://www.bitcoinabuse.com/reports"],
							["https://checkbitcoinaddress.com/abuse-reports-to-bitcoin-address?page=1"],
							["https://www.cryptoblacklist.io/en/bitcoin/"],
							["https://www.cryptoblacklist.io/en/ethereum-blacklist"],
							["http://ssrg.site.uottawa.ca/bgsieeesb2020/scamAddresses.txt"],
							["http://ssrg.site.uottawa.ca/bgsieeesb2020/transactionlessScamAddresses.txt"],
							["http://ssrg.site.uottawa.ca/bgsieeesb2020/notBitcoinAddresses.txt"],
							["https://bitcoinais.com/page/1"],
							["https://api.cryptoscamdb.org/v1/addresses"],
							["https://cryptscam.com/detail/"],
							["https://cryptscam.com/en?page=1"],
							["https://www.seekoin.com/address.php"],
							["https://www.bitcoinwhoswho.com/address/"]
						]
					]
				},
				{
					"table_name": "source_label_url",
					"create": [
						"source_label_url_id SMALLSERIAL",
						"source_label_id SMALLINT NOT NULL",
						"url_id BIGINT NOT NULL",
						"roles SMALLINT[] NOT NULL",
						"last_crawled_at TIMESTAMP",
						"CONSTRAINT source_label_url_id_pkey PRIMARY KEY (source_label_url_id)",
						"CONSTRAINT source_label_url_source_label_id_fkey FOREIGN KEY (source_label_id) REFERENCES source_label (source_label_id)",
						"CONSTRAINT source_label_url_url_id_fkey FOREIGN KEY (url_id) REFERENCES url (url_id)",
						"CONSTRAINT source_label_url_source_label_id_url_id_key UNIQUE (source_label_id, url_id)",
						"CONSTRAINT source_label_url_source_label_id_check CHECK (source_label_id > 0)",
						"CONSTRAINT source_label_url_url_id_check CHECK (url_id > 0)"
					],
					"insert": [
						["source_label_id", "url_id", "roles"],
						[
							[1, 1, "{}"],
							[1, 2, "{}"],
							[2, 3, "{}"],
							[3, 4, "{}"],
							[4, 5, "{}"],
							[5, 6, "{}"],
							[6, 7, "{}"],
							[6, 8, "{}"],
							[7, 9, "{}"],
							[8, 10, "{}"],
							[9, 11, "{}"],
							[10, 12, "{}"],
							[11, 13, "{}"],
							[12, 14, "{}"],
							[13, 15, "{}"]
						]
					]
				},
				{
					"table_name": "data",
					"create": [
						"data_id BIGSERIAL",
						"source_label_url_id SMALLINT NOT NULL",
						"url_id BIGINT NOT NULL",
						"roles SMALLINT[] NOT NULL",
						"path TEXT NOT NULL",
						"crawled_at TIMESTAMP",
						"CONSTRAINT data_data_id_pkey PRIMARY KEY (data_id)",
						"CONSTRAINT data_source_label_url_id_fkey FOREIGN KEY (source_label_url_id) REFERENCES source_label_url (source_label_url_id)",
						"CONSTRAINT data_url_id_fkey FOREIGN KEY (url_id) REFERENCES url (url_id)",
						"CONSTRAINT data_source_label_url_id_check CHECK (source_label_url_id > 0)",
						"CONSTRAINT data_url_id_check CHECK (url_id > 0)"
					]
				}
			]
		}
	]
}